setup.py
sphaira/__init__.py
sphaira/convert.py
sphaira/cube_map.py
sphaira/equirect.py
sphaira/external.c
sphaira/geom.py
sphaira/glsl.py
sphaira/healpix.py
sphaira/layer.py
sphaira/projection.py
sphaira/view.py
sphaira.egg-info/PKG-INFO
sphaira.egg-info/SOURCES.txt
sphaira.egg-info/dependency_links.txt
sphaira.egg-info/entry_points.txt
sphaira.egg-info/requires.txt
sphaira.egg-info/top_level.txt