Metadata-Version: 1.1
Name: sphaira
Version: 0.3.2
Summary: Work with spherical images.
Home-page: http://sphaira.org
Author: Mate Kovacs
Author-email: mkovaxx@gmail.com
License: BSD
Platform: UNKNOWN
Classifier: Development Status :: 3 - Alpha
Classifier: Intended Audience :: End Users/Desktop
Classifier: License :: OSI Approved :: BSD License
Classifier: Natural Language :: English
Classifier: Operating System :: POSIX
Classifier: Programming Language :: Python :: 2.7
Classifier: Topic :: Multimedia
